{
  "Badische Landesbibliothek": {
    "Matches": [],
    "Non-matches": []
  },
  "Biblioteca dell'Abbazia benedettina di S. Georgenberg-Fiecht": {
    "Matches": [],
    "Non-matches": []
  },
  "Biblioteka Jagiello\u0144ska": {
    "Matches": [],
    "Non-matches": []
  },
  "Biblioteca Durazzo": {
    "Matches": [
      "Genova (I), Biblioteca Durazzo"
    ],
    "Non-matches": []
  },
  "Biblioteca P\u00fablica Municipal": {
    "Matches": [],
    "Non-matches": []
  },
  "Gottfried Wilhelm Leibniz Bibliothek": {
    "Matches": [],
    "Non-matches": []
  },
  "Corpus Christi College Library": {
    "Matches": [
      "CAMBRIDGE, Parker Library (at Corpus Christi College)"
    ],
    "Non-matches": [
      "CAMBRIDGE, Fitzwilliam Museum",
      "Canterbury, Benedictine abbey of St. Augustine",
      "Episcopal Divinity School",
      "Episcopal Theological School (Cambridge, Mass.)",
      "Catalogi librorum manuscriptorum angliae et hiberniae, v. 2 (E. Bernard)",
      "Cambridge University, Library",
      "London, Bernard Quaritch Ltd. (1847-)",
      "Biblioteca Trivulziana",
      "Sotheby's (London, etc.)",
      "National Art-Collections Fund (Great Britain)",
      "Sothebys New York",
      "Librairie et imprimerie Firmin Didot",
      "William H. Robinson Limited",
      "Fitzwilliam Museum. Friends",
      "Catalogi librorum manuscriptorum angliae et hiberniae, v. 1 (E. Bernard)",
      "Catalogue of the printed books and manuscripts bequeathed by Francis Douce, esq.",
      "University of Oxford",
      "W\u00fcrzburg, cathedral church of St. Kilian"
    ]
  },
  "Biblioteca del Museo Correr": {
    "Matches": [],
    "Non-matches": [
      "Venezia, Biblioteca Nazionale Marciana"
    ]
  },
  "Biblioteka Gdanska Polskiej Akademii Nauk  ": {
    "Matches": [],
    "Non-matches": []
  },
  "Archivio di Stato": {
    "Matches": [],
    "Non-matches": [
      "Inventari dei manoscritti delle biblioteche dItalia (G. Mazzotinti), v. 1",
      "Biblioteca comunale di Gubbio",
      "Biblioteca comunale di Gubbio, Fondo dellex-convento di S. Pietro"
    ]
  },
  "Biblioteka K\u00f3rnicka Polskiej Akademii Nauk": {
    "Matches": [],
    "Non-matches": []
  },
  "Eton College Library": {
    "Matches": [],
    "Non-matches": []
  },
  "Stiftsbibliotheck": {
    "Matches": [],
    "Non-matches": []
  },
  "Staatsbibliothek - Preu\u00dfischer Kulturbesitz": {
    "Matches": [
      "BERLIN, Staatsbibliothek zu Berlin - Preussischer Kulturbesitz",
      "Berlin, Staatsbibliothek zu Berlin - Preussischer Kulturbesitz"
    ],
    "Non-matches": [
      "BERN, Burgerbibliothek",
      "Deutsche Staatsbibliothek",
      "",
      "Augustinian nuns at Coesfeld",
      "Martin Breslauer (Berlin)",
      "K\u00f6nigliches Museum (Royal Museum), Berlin",
      "Pierpont Morgan Library",
      "Staatsbibliothek zu Berlin",
      "Beckford Collection, Hamilton Palace",
      "London, British Library",
      "London, Bernard Quaritch Ltd. (1847-)",
      "Ottobeuren Abbey (Benedictine)",
      "Sotheby's (London, etc.)",
      "The Rosenbach Company",
      "Rosenbach Museum & Library",
      "Oberlin College",
      "Trier, Saint-Maximin (abbaye)",
      "Carthusians of the Trinit\u00e9 (Dijon)",
      "London, J. & J. Leighton",
      "Librairie et imprimerie Firmin Didot",
      "Graves Art Gallery",
      "Paris, Jesuit college of Clermont",
      "Auctionata",
      "Franciscans",
      "Jacques Rosenthal (Firm)",
      "De Bure",
      "Henry E. Huntington Library and Art Gallery.",
      "Princeton University"
    ]
  },
  "Archivio storico della Provincia di Cristo Re dei Frati Minori dell'Emilia Romagna": {
    "Matches": [],
    "Non-matches": [
      "Inventari dei manoscritti delle biblioteche dItalia (L. Frati), v. 14",
      "BOLOGNA, Biblioteca Comunale dell'Archiginnasio",
      "Biblioteca Arcivescovile (Bologna, Italy)"
    ]
  },
  "Casa Cavalli": {
    "Matches": [],
    "Non-matches": []
  },
  "Dominikanerkonvent": {
    "Matches": [
      "Dominikanerkloster (Vienna)"
    ],
    "Non-matches": []
  },
  "M\u00e9diath\u00e8que Jos\u00e9-Cabanis": {
    "Matches": [],
    "Non-matches": []
  },
  "Cathedral and Chapter Library": {
    "Matches": [],
    "Non-matches": []
  },
  "Biblioteche Riunite Civica e Antonio Ursino Recupero": {
    "Matches": [],
    "Non-matches": []
  },
  "Nieders\u00e4chsische Staats- und Universit\u00e4tsbibliothek": {
    "Matches": [],
    "Non-matches": [
      "Gotha, Forschungsbibliothek"
    ]
  },
  "M\u00e9diath\u00e8que Verlaine": {
    "Matches": [],
    "Non-matches": []
  },
  "Biblioteka Zakladu Narodowego im. Ossolinskich (Ossolineum)": {
    "Matches": [],
    "Non-matches": []
  },
  "Archivio Storico Civico e Biblioteca Trivulziana": {
    "Matches": [],
    "Non-matches": [
      "MILANO, Biblioteca Ambrosiana"
    ]
  },
  "Stiftsbibliothek": {
    "Matches": [],
    "Non-matches": []
  },
  "Biblioth\u00e8que Municipale": {
    "Matches": [],
    "Non-matches": [
      "Catalogue general des manuscrits des bibliotheques publiques de France, v. 4, Nancy"
    ]
  },
  "M\u00e9diath\u00e8que de l'Abbaye Saint-Vaast": {
    "Matches": [],
    "Non-matches": []
  },
  "Nieders\u00e4chsische Landesarchiv\u00a0": {
    "Matches": [],
    "Non-matches": []
  },
  "Harvard University Library": {
    "Matches": [
      "Cambridge University, Library",
      "Cambridge (Mass.), Harvard University",
      "Cambridge (US-MA), Houghton Library, Harvard University",
      "Cambridge, University",
      "Emmanuel College (University of Cambridge)",
      "Jesus College University of Cambridge",
      "Peterhouse (University of Cambridge)"
    ],
    "Non-matches": [
      "CAMBRIDGE, Fitzwilliam Museum",
      "Canterbury, Benedictine abbey of St. Augustine",
      "CAMBRIDGE, Parker Library (at Corpus Christi College)",
      "Cambridge (GB), Trinity College, Wren Library",
      "Gonville and Caius College, Cambridge",
      "Boston Medical Library",
      "Harvard Medical School",
      "Jacques Rosenthal (Firm)",
      "Catalogi librorum manuscriptorum angliae et hiberniae, v. 2 (E. Bernard)",
      "Cambridge, Corpus Christi College",
      "SDBM source 13590",
      "St. Albans, Benedictine Abbey",
      "Cambridge, King's College",
      "Cambridge, Pembroke College",
      "Harvard College Library",
      "Houghton Library",
      "Harvard Law School",
      "Maggs (Librairie)",
      "Newnham College",
      "Augustinian house at Certaldo",
      "London, Bernard Quaritch Ltd. (1847-)",
      "Abbey St Illidius (Clermont-Ferrand)",
      "Sotheby, Wilkinson & Hodge"
    ]
  },
  "Biblioth\u00e8que des Dominicains ": {
    "Matches": [],
    "Non-matches": []
  },
  "University Library": {
    "Matches": [
      "Cambridge, University",
      "Glasgow, University Library (1475-)",
      "Princeton University",
      "Sydney, University Library (Fisher Library)"
    ],
    "Non-matches": []
  },
  "Biblioteca Statale": {
    "Matches": [],
    "Non-matches": []
  },
  "Universitetsbibliotek": {
    "Matches": [
      "GOETTINGEN, Nieders\u00e4chsische Staats-und Universit\u00e4tsbibliothek"
    ],
    "Non-matches": []
  },
  "Gr\u00e4flich Sch\u00f6nbornsche Bibliothek": {
    "Matches": [],
    "Non-matches": []
  },
  "Butler Library": {
    "Matches": [],
    "Non-matches": [
      "Vente, New York, Christie's, 2006, 27 juin",
      "London, Bernard Quaritch Ltd. (1847-)",
      "Sotheby's (London, etc.)",
      "New York, Public Library",
      "Rosenthal",
      "",
      "Pierpont Morgan Library"
    ]
  },
  "N\u00e1rodn\u00ed Knihovna Cesk\u00e9 Republiky": {
    "Matches": [],
    "Non-matches": []
  },
  "Mus\u00e9e des Arts Anciens ": {
    "Matches": [],
    "Non-matches": [
      "Namur, Fonds de la Ville"
    ]
  },
  "Biblioth\u00e8que municipale": {
    "Matches": [],
    "Non-matches": []
  },
  "University of Manchester Library": {
    "Matches": [
      "MANCHESTER, John Rylands University Library"
    ],
    "Non-matches": []
  },
  "M\u00e9diath\u00e8que Municipale Jean L\u00e9vy": {
    "Matches": [],
    "Non-matches": []
  },
  "Bayerische Staatsbibliothek": {
    "Matches": [
      "MUENCHEN, Bayerische Staatsbibliothek"
    ],
    "Non-matches": [
      "",
      "Abbaye Notre-Dame d'Acey (Vitreux, Jura)",
      "Jacques Rosenthal (Firm)",
      "Martin Breslauer, Inc.",
      "Abbey of St. Peter, Erfurt, Germany",
      "Rosenthal",
      "Dominikanerkirche St. Blasius (Regensburg)",
      "Leo S. Olschki (Firm)",
      "Kgl. Hof- und Staatsbibliothek in M\u00fcnchen",
      "Librairie et imprimerie Firmin Didot",
      "Weiss & Co. Antiquariat (Munich)",
      "Wellesley College",
      "Potier",
      "Reichskartause Buxheim (Carthusian monastery, Buxheim)"
    ]
  },
  "Staats- und Stadtbibliothek": {
    "Matches": [
      "Staats- und Stadtbibliothek Augsburg",
      "Staats-, Kreis- und Stadtbibliothek Augsburg"
    ],
    "Non-matches": [
      "Catalogus Graecorum librorum, manuscriptorum Augustinae bibliothecae",
      "St. Ulrichs and St. Afras Abbey"
    ]
  },
  "Lincoln College Library": {
    "Matches": [
      "Oxford, Lincoln College"
    ],
    "Non-matches": [
      "University of Oxford",
      "Abingdon, Benedictine abbey"
    ]
  },
  " \u00d6sterreichische Nationalbibliothek ": {
    "Matches": [
      "Wien, \u00d6sterreichische Nationalbibliothek"
    ],
    "Non-matches": []
  },
  "Biblioth\u00e8que Cantonale et Universitaire": {
    "Matches": [],
    "Non-matches": []
  },
  "Egyh\u00e1zmegyei Kincst\u00e1r \u00e9s K\u00f6nyvt\u00e1r": {
    "Matches": [],
    "Non-matches": []
  },
  "Pr\u00e4monstratenser-Stiftsbibliothek": {
    "Matches": [],
    "Non-matches": []
  },
  "Balliol College Library": {
    "Matches": [],
    "Non-matches": [
      "Catalogi librorum manuscriptorum angliae et hiberniae, v. 1 (E. Bernard)",
      "Catalogue of the printed books and manuscripts bequeathed by Francis Douce, esq.",
      "Maggs (Librairie)",
      "OSLO, Sch\u00f8yen Collection",
      "London, Bernard Quaritch Ltd. (1847-)",
      "Sotheby's (London, etc.)",
      "Canterbury, Christ Church Cathedral Priory (Benedictine)",
      "Canterbury Cathedral",
      "Sanders of Oxford",
      "Canterbury Cathedral Library",
      "Bloomsbury Book Auctions (Firm)",
      "Oxford, St. John's College",
      "Louvain, Park abbey"
    ]
  },
  "Biblioteca Nazionale Marciana": {
    "Matches": [
      "Venezia, Biblioteca Nazionale Marciana"
    ],
    "Non-matches": [
      "London, Bernard Quaritch Ltd. (1847-)",
      "Venice, church of SS Giovanni e Paolo",
      "Pierpont Morgan Library",
      "Les Enluminures Ltd.",
      "Anderson Auction Company",
      "Dominican Convent of SS. Giovanni e Paolo (Venice)",
      "Haverhill Public Library"
    ]
  },
  "Biblioteca Comunale Aurelio Saffi": {
    "Matches": [],
    "Non-matches": []
  },
  "Martinus-Bibliothek": {
    "Matches": [],
    "Non-matches": [
      "Mainz, Carthusian abbey of St Michael"
    ]
  },
  "Biblioteca Universitaria": {
    "Matches": [
      "Universit\u00e0 di Urbino"
    ],
    "Non-matches": [
      "Urbino Fondo Del Comune",
      "BOLOGNA, Biblioteca Comunale dell'Archiginnasio"
    ]
  },
  "Bibliothek des St. Nikolaus-Hospitals": {
    "Matches": [],
    "Non-matches": [
      "Deutsche Staatsbibliothek"
    ]
  },
  "The Morgan Library & Museum": {
    "Matches": [],
    "Non-matches": [
      "London, Bernard Quaritch Ltd. (1847-)"
    ]
  },
  "Topkap\u0131 Saray\u0131 M\u00fczesi K\u00fct\u00fcphanesi": {
    "Matches": [],
    "Non-matches": []
  },
  "Real Biblioteca del Monasterio de San Lorenzo de El Escorial": {
    "Matches": [
      "El Escorial (E), Real Biblioteca del Monasterio de San Lorenzo",
      "El Escorial, Real Biblioteca del Monasterio de San Lorenzo"
    ],
    "Non-matches": []
  },
  "Marsh's Library": {
    "Matches": [],
    "Non-matches": []
  },
  "Biblioteca Nazionale Centrale": {
    "Matches": [
      "Firenze (I), Biblioteca Nazionale Centrale",
      "Biblioteca Nazionale Centrale, Firenze, Italy"
    ],
    "Non-matches": [
      "Biblioteca Riccardiana",
      "Leo S. Olschki (Firm)",
      "Riccardi family",
      "Florence, Convento di San Marco",
      "",
      "Census of Medieval and Renaissance Manuscripts in the United States and Canada, vol. II (S. De Ricci)",
      "Firenze, Biblioteca Medicea Laurenziana",
      "Biblioteca Medicea Laurenziana, Florence",
      "University of Chicago (1890-)",
      "James & Mary Lee Tregaskis Booksellers",
      "Hoepli (1870-)",
      "University of Chicago Library",
      "Payne and Foss",
      "Chiesa di San Marco (Milan, Italy)",
      "Ballarat Fine Art Gallery",
      "Olschki",
      "Libreria Antiquaria T. De Marinis",
      "Istituto italiano del libro (Florencja).",
      "Librairie Damasc\u00e8ne Morgand",
      "Pierpont Morgan Library",
      "London, J. & J. Leighton",
      "Cochon family",
      "Florence, Camaldolese convent of S. Maria degli Angeli"
    ]
  },
  "Zisterzienserstift": {
    "Matches": [],
    "Non-matches": []
  },
  "Bibliothek des Zisterzienserstifts": {
    "Matches": [],
    "Non-matches": []
  },
  "M\u00e9diath\u00e8que Toussaint": {
    "Matches": [],
    "Non-matches": [
      "Angers, Saint-Aubin, inventaire du 12e s."
    ]
  },
  "Biblioteca Casanatense": {
    "Matches": [],
    "Non-matches": [
      "Catalogus selectissimae bibliothecae Nicholai Rossi, pt. 1",
      "",
      "Biblioteca angelica (Rome, Italy)",
      "The Romantic Agony",
      "Virtue and Cahill Library, St. John the Evangelist Roman Catholic Cathedral, Portsmouth",
      "ROMA, Biblioteca Nazionale Centrale 'Vittorio Emanuele II'",
      "Payne and Foss",
      "Abbazia di Nonantola",
      "Biblioteca Sessoriana",
      "Sotheby's (London, etc.)",
      "Antiquariaat Meijer Elte (Den Haag)",
      "Southwark, Roman Catholic Metropolitan See",
      "London, Bernard Quaritch Ltd. (1847-)",
      "New York, The Brooklyn Museum",
      "Rome, church of Santa Cecilia in Trastevere",
      "Biblioteca comunale di Savigno di Romagna",
      "Rome, Collegium Romanum Societatis Jesu",
      "Yale University",
      "San Gregorio al Celio (Abbey : Rome, Italy)",
      "Art Institute of Chicago",
      "Princeton University"
    ]
  },
  "\u00a0Ratsschulbibliothek (Stadtarchiv)": {
    "Matches": [],
    "Non-matches": []
  },
  "College of Arms": {
    "Matches": [],
    "Non-matches": [
      "British Museum",
      "CAMBRIDGE, Fitzwilliam Museum",
      "London, Bernard Quaritch Ltd. (1847-)",
      "Clare Priory",
      "ABERDEEN, University Library",
      "Aberdeen, Marischal College",
      "London, cathedral church of St Paul",
      "London, British Library",
      "Ellis & Elvey (librairie, Angleterre, fin 19e s.)",
      "Librairie et imprimerie Firmin Didot",
      "Walters Art Gallery",
      "Baltimore, The Walters Art Museum",
      "Leo S. Olschki (Firm)",
      "Olschki",
      "Maggs (Librairie)",
      "Cambridge (Mass.), Harvard University",
      "Ellis",
      "Librairie Sourget",
      "James & Mary Lee Tregaskis Booksellers",
      "Sotheby's (London, etc.)",
      "Les Enluminures Ltd.",
      "Morimondo, Cistercian abbey",
      "Christie's",
      "Fenwick family",
      "Monast\u00e8re des Emmur\u00e9es Rouen",
      "Arader Galleries",
      "Convent of St. Matthew",
      "London, J. & J. Leighton",
      "Marc Antoine du Ry Medieval Art (Firm)",
      "University of Chicago (1890-)",
      "University of Chicago Library",
      "Karl W. Hiersemann (Firm)",
      "Nicolas Rauch S.A.",
      "Jonathan A. Hill, Inc.",
      "London school of Jewish studies",
      "Sam Fogg Rare Books & Manuscripts",
      "Reiss & Sohn",
      "University of Kansas",
      "E.P. Goldschmidt & Co.",
      "",
      "Catalogue of the Library at Seaford House Belgrave Square S.W.",
      "Medieval Manuscripts in British Libraries, v.1, London (N.R.Ker)",
      "Census of Medieval and Renaissance Manuscripts in the United States and Canada, vol. II (S. De Ricci)",
      "Phillipps manuscripts : Catalogus librorum manuscriptorum in bibliotheca D. Thomae Phillipps, Bt., impressum Typis Medio-Montanis, 1837-1871 (intro. by A.N.L. Munby)",
      "Arcadian Library Online",
      "Mughal and Other Indian Paintings",
      "A Catalogue of manuscripts forming a portion of the library of Robert Hoe (R. Hoe and C. Shipman)",
      "'s-Gravenhage, Koninklijke Bibliotheek",
      "York Minster Library",
      "Abbaye Saint-Martin (Laon)",
      "Abbey of St. Peter, Erfurt, Germany",
      "Biblioteca Trivulziana",
      "George A. Leavitt & Co.",
      "Bloomsbury Book Auctions (Firm)",
      "British Museum. Department of Manuscripts",
      "Bruxelles, Biblioth\u00e8que royale de Belgique",
      "Benediktinerabtei Irsee",
      "National Art-Collections Fund (Great Britain)",
      "Sothebys New York",
      "Santa Maria delle Grazie (Milan)",
      "Cattedrale di San Romolo a Fiesole (Italy)",
      "J\u00f6rn G\u00fcnther Antiquariat (Firm)",
      "Dreweatts & Bloomsbury Auctions (Firm)",
      "Doyle New York",
      "Florence, Convento di San Marco",
      "Payne and Foss",
      "Furstenberg (Donaueschingen)",
      "Harding and Lepard, Messrs.",
      "Harrow School",
      "Henry E. Huntington Library and Art Gallery.",
      "Hodgson's (1807-1967)",
      "Inner Temple",
      "Internationaal Antiquariaat (Menno Hertzberger & Co.)  (1920-1970)",
      "National Museum, Stockholm",
      "J. I. Davis & G. M. Orioli (firm)",
      "K\u00f6ln, Carthusian abbey",
      "LONDON, Lambeth Palace Library",
      "London, Sion College",
      "H.P. Kraus (Firm)",
      "Jacques Rosenthal (Firm)",
      "Yale University",
      "Potier",
      "Benediktinerabtei Weingarten",
      "Pierpont Morgan Library",
      "Bruton Abbey",
      "Sotheby, Wilkinson & Hodge",
      "Christies",
      "University of Pennsylvania, Library, Kislak Center for Special Collections, Rare Books and Manuscripts",
      "University of Pennsylvania",
      "Ellis and Scrutton",
      "Dodd, Mead & Company.",
      "Houghton Library",
      "Leclerc",
      "Liverpool Public Libraries",
      "Oxford, The Bodleian Library",
      "Libreria Antiquaria T. De Marinis",
      "Padua, Benedictine abbey of Santa Guistina",
      "Fountains Abbey (Cistercian)",
      "Techener",
      "Thorold (Syston Park)",
      "W. & G. Foyle Ltd",
      "Abbaye de Maubuisson",
      "Bradenstoke Priory",
      "Bury St Edmunds, Benedictine abbey",
      "Byland Abbey (North Yorkshire, England)",
      "Canterbury, Benedictine abbey of St. Augustine",
      "Priverno, Cisterican abbey of San Stefano, Fossanova",
      "Ely Cathedral",
      "Gloucester Cathedral",
      "Gloucester, Benedictine Abbey of St. Peter",
      "Winchcombe, Benedictine abbey",
      "Merton Priory",
      "Ramsey, Benedictine Abbey",
      "Reading, Benedictine abbey",
      "Rochester Cathedral",
      "Salisbury, cathedral church",
      "St. Albans, Benedictine Abbey",
      "Royal Society Great Britain",
      "Worcester, Benedictine cathedral priory of St Mary",
      "London, Sokol Books",
      "Monastery St. Ambrosius Major (Milan)",
      "C\u00eeteaux, Notre-Dame, abbaye O.Cist. (H)",
      "Messrs. Evans (Firm)",
      "Robinson Brothers",
      "Martin Breslauer (London)",
      "Nassauisches Kunstauktionshaus Witte & Co",
      "National Archives (Great Britain)",
      "New York, General Theological Seminary",
      "Monastery of Great Lavra, Mount Athos (St. Athanasius)",
      "Christies New York",
      "New York, House of El Dieff (librairie)",
      "University of Texas at Austin, Harry Ransom Humanities Research Center",
      "The Rosenbach Company",
      "University of Texas at Austin",
      "New York, Public Library",
      "PARIS, Biblioth\u00e8que nationale de France, Manuscrits",
      "Ch\u00e2teau de Rosny-sur-Seine. Biblioth\u00e8que",
      "Paris, Augustinian abbey of St.-Victor",
      "Paris, Jesuit college of Clermont",
      "Duke University. Rare Book, Manuscript, and Special Collections Library",
      "Plymouth Free Public Library",
      "Puttick & Simpson, maison de vente (London)",
      "National Library of South Africa",
      "Roseberys",
      "S. Leigh Sotheby & John Wilkinson",
      "Sankt Florian, abbaye O.S.A.",
      "Augustiner Kloster Allerheiligen (Freiburg im Breisgau)",
      "Silberstein-Boesky Charitable Foundation",
      "Solomons & Berkelouw",
      "British Rail (Firm). Pension Fund",
      "William S. K\u00fcndig (Firm)",
      "Coleccion Suarez Aguirre",
      "Monastery Quinze-Vingt",
      "Steinfeld (in Kall), Premonstratensian abbey",
      "St. Marys Seminary",
      "Staatsbibliothek zu Berlin",
      "Beckford Collection, Hamilton Palace",
      "Cornell University",
      "Monasteriorum Allemanniae",
      "University of London",
      "University College, London",
      "University of North Carolina at Chapel Hill",
      "Victoria and Albert Museum. National Art Library",
      "Victoria & Albert Museum",
      "Wellcome Historical Medical Library",
      "Westminster, Benedictine Abbey",
      "Yale Law School",
      "Weissenau Abbey",
      "Rosenthal",
      "Librairie Andr\u00e9 Cottet",
      "Metropolitan Museum of Art (New York)",
      "New York, The Brooklyn Museum",
      "Rome, church of Santa Cecilia in Trastevere",
      "Brown University",
      "John Carter Brown Library",
      "Philadelphia Museum of Art",
      "Francis Edwards, Ltd.",
      "Swann Galleries",
      "John Windle (Firm)",
      "LOS ANGELES, J. Paul Getty Museum",
      "Martin Breslauer, Inc.",
      "Free Library of Philadelphia",
      "Zeitlin & Ver Brugge",
      "Martayan Lan (Firm)",
      "William Patrick Watson Antiquarian Books",
      "Antiquariat Inlibris",
      "Folger Shakespeare Library",
      "Clumber Park Library"
    ]
  },
  "Biblioteca Apostolica Vaticana": {
    "Matches": [
      "Bibliotheca Apostolica Vaticana",
      "VATICANO (CITTA DEL), Biblioteca apostolica Vaticana",
      "Vaticano (Citt\u00e0 del), Biblioteca apostolica Vaticana"
    ],
    "Non-matches": []
  },
  "Kongelige Bibliotek": {
    "Matches": [],
    "Non-matches": []
  },
  "Th\u00fcringer Universit\u00e4ts- und Landesbibliothek": {
    "Matches": [],
    "Non-matches": []
  },
  "Biblioteca Statale Oratoriana dei Girolamini": {
    "Matches": [],
    "Non-matches": [
      "Census of Medieval and Renaissance Manuscripts in the United States and Canada, vol. I (S. De Ricci)",
      "PARIS, Biblioth\u00e8que nationale de France, Manuscrits",
      "Aragonese kings of Naples",
      "Biblioth\u00e8que royale de Blois"
    ]
  },
  "Istituto Barbara Melzi": {
    "Matches": [],
    "Non-matches": []
  },
  "Bibliothek des Augustiner Chorherrenstiftes": {
    "Matches": [],
    "Non-matches": []
  },
  "British Library": {
    "Matches": [
      "London, British Library"
    ],
    "Non-matches": [
      "Supplement to the Census of Medieval and Renaissance Manuscripts in the United States and Canada (C.U. Faye and W.H. Bond)",
      "Sotheby's (London, etc.)",
      "Zeitlin & Ver Brugge",
      "Martayan Lan (Firm)",
      "William Patrick Watson Antiquarian Books",
      "Antiquariat Inlibris",
      "London, Bernard Quaritch Ltd. (1847-)"
    ]
  },
  "Biblioteca del Monumento Nazionale del Monastero di Santa Scolastica": {
    "Matches": [],
    "Non-matches": []
  },
  "Burgerbibliothek": {
    "Matches": [
      "Bern, Burgerbibliothek"
    ],
    "Non-matches": [
      "Deutsche Staatsbibliothek",
      "London, Bernard Quaritch Ltd. (1847-)",
      "Petworth House",
      "University of Pennsylvania, Library, Kislak Center for Special Collections, Rare Books and Manuscripts",
      "University of Pennsylvania",
      "Cambridge (Mass.), Harvard University",
      "London, J. & J. Leighton",
      "Maggs (Librairie)",
      "Ellis",
      "Dawsons (libraire, Pall Mall, Londres)",
      "John Howell Books (Firm)",
      "J. I. Davis & G. M. Orioli (firm)",
      "J. Pearson & Co.",
      "Pierpont Morgan Library",
      "Sotheby's (London, etc.)",
      "Columbia University",
      "Abbey Santa Mar\u00eda de Benev\u00edvere",
      "Free Library of Philadelphia",
      "Louvain, Park abbey",
      "York Minster Library",
      "Payne and Foss"
    ]
  },
  "Bistumsarchiv": {
    "Matches": [],
    "Non-matches": []
  },
  "Holkham Hall": {
    "Matches": [],
    "Non-matches": []
  },
  "Biblioteca Comunale Ariostea": {
    "Matches": [],
    "Non-matches": []
  },
  "Det Kgl. Bibliotek": {
    "Matches": [],
    "Non-matches": []
  },
  "Le Labo - Cambrai": {
    "Matches": [],
    "Non-matches": [
      "Cambrai (F), Biblioth\u00e8que municipale"
    ]
  },
  "Real Biblioteca (Biblioteca de Palacio)": {
    "Matches": [],
    "Non-matches": [
      "Cathedral of Toledo",
      "Ferrandez Biblioteca de La Santa Iglesia Catedral (Toledo)",
      "Madrid, Biblioteca Nacional de Espa\u00f1a"
    ]
  },
  "Biblioth\u00e8que nationale de France": {
    "Matches": [
      "Paris, Biblioth\u00e8que nationale de France, Manuscrits",
      "PARIS, Biblioth\u00e8que nationale de France, Manuscrits",
      "Paris (F), Biblioth\u00e8que nationale de France, Manuscrits",
      "Paris, Biblioth\u00e8que nationale de France, Manuscrits, lat. 02389",
      "Biblioth\u00e8que du roi (France)",
      "Bibliotheque nationale de France, Archives et Manuscrits (Online Catalogue)"
    ],
    "Non-matches": [
      "",
      "Catalogue de la biblioth\u00e8que du coll\u00e8ge de Sorbonne (1338), I",
      "Catalogue de la biblioth\u00e8que du coll\u00e8ge de Sorbonne (1338), LIIII",
      "Catalogue de la biblioth\u00e8que du coll\u00e8ge de Sorbonne (1338), LVI",
      "Librairie et imprimerie Firmin Didot",
      "Paris, Augustinian abbey of St.-Victor",
      "Paris, Jesuit college of Clermont",
      "Alde",
      "Biblioth\u00e8que municipale dOrl\u00e9ans ",
      "De Bure",
      "Leclerc",
      "Monast\u00e8re des C\u00e9lestins Paris",
      "Biblioth\u00e8que de lArsenal",
      "Potier",
      "Silvestre, Maison de vente",
      "R\u00e9pertoire m\u00e9thodique de la librairie Damasc\u00e8ne Morgand",
      "Louvain, Park abbey",
      "Monasterio de Santa Mar\u00eda de El Paular",
      "Pierpont Morgan Library",
      "Rosenthal",
      "Paris (F), Biblioth\u00e8que Mazarine",
      "Galerie Fischer",
      "LArt Ancien / Haus der B\u00fccher",
      "Christies Paris",
      "Couvent Saint-Jacques (Paris ; 1217-1791)",
      "London, British Library",
      "Paris (F), Biblioth\u00e8que de l'Arsenal",
      "Biblioth\u00e8que Mazarine, Paris (1643- )",
      "Catalogue de la biblioth\u00e8que du coll\u00e8ge de Sorbonne (1338), XXIV",
      "Paris, Binoche et Giquello (maison de vente)",
      "Agen, Jesuit College",
      "Abbaye de Marmoutier (Tours)",
      "Ch\u00e2teau de Rosny-sur-Seine. Biblioth\u00e8que",
      "Techener"
    ]
  },
  "Zentral- und Hochschulbibliothek": {
    "Matches": [],
    "Non-matches": [
      "Galerie Fischer"
    ]
  },
  "Stadtbibliothek": {
    "Matches": [],
    "Non-matches": []
  },
  " Beinecke Rare Book and Manuscript Library": {
    "Matches": [],
    "Non-matches": [
      "",
      "A Gathering of Medieval English Manuscripts: The Takamiya Collection at the Beinecke Library",
      "London, Bernard Quaritch Ltd. (1847-)",
      "Yale University",
      "Yale Medical Library. Historical Library",
      "Bibliotheca Apostolica Vaticana",
      "Internationaal Antiquariaat (Menno Hertzberger & Co.)  (1920-1970)",
      "Sotheby's (London, etc.)",
      "Yale Library Associates"
    ]
  },
  "Biblioteca Civica Berio": {
    "Matches": [],
    "Non-matches": []
  },
  "Biblioth\u00e8que Nationale": {
    "Matches": [],
    "Non-matches": []
  },
  "Archivo-Biblioteca de la Santa Iglesia Catedral": {
    "Matches": [],
    "Non-matches": []
  },
  "Staats- und Universit\u00e4tsbibliothek": {
    "Matches": [],
    "Non-matches": []
  },
  "Universiteitsarchief KU Leuven": {
    "Matches": [
      "University of Illinois at Urbana-Champaign"
    ],
    "Non-matches": [
      "Leuven (B), Maurits Sabbebibliotheek (KULeuven)",
      "London, Bernard Quaritch Ltd. (1847-)",
      "Louvain, Park abbey",
      "Maggs (Librairie)",
      "CAMBRIDGE, Fitzwilliam Museum",
      "Sotheby's (London, etc.)"
    ]
  },
  "Walters Art Museum": {
    "Matches": [],
    "Non-matches": [
      "London, Bernard Quaritch Ltd. (1847-)",
      "San Giorgio Maggiore",
      "Rolandi, Pietro",
      "Rosenthal",
      "Walters Art Gallery",
      "Leo S. Olschki (Firm)",
      "Olschki"
    ]
  },
  "Universit\u00e4tsbibliothek": {
    "Matches": [
      "Universit\u00e4tsbibliothek, Basel, Switzerland",
      "Basel (CH), Universit\u00e4tsbibliothek",
      "W\u00fcrzburg, University Library (Universit\u00e4tsbibliothek)",
      "Leipzig, Universit\u00e4tsbibliothek",
      "Leiden, Universiteitsbibliotheek"
    ],
    "Non-matches": [
      ""
    ]
  },
  "M\u00e9diath\u00e8que L'Apostrophe": {
    "Matches": [],
    "Non-matches": []
  },
  "\u00a0Saint Bonaventure University": {
    "Matches": [],
    "Non-matches": []
  },
  "W\u00fcrttembergische Landesbibliothek": {
    "Matches": [
      "STUTTGART, W\u00fcrttembergische Landesbibliothek"
    ],
    "Non-matches": []
  },
  " Stadtbibliothek": {
    "Matches": [
      "Stadtbibliothek N\u00fcrnberg"
    ],
    "Non-matches": [
      ""
    ]
  },
  "National Maritime Museum": {
    "Matches": [],
    "Non-matches": []
  },
  "Museo Cond\u00e9": {
    "Matches": [],
    "Non-matches": []
  },
  "Wissenschaftliche Allgemein-Bibliothek der Stadt Erfurt": {
    "Matches": [],
    "Non-matches": [
      "London, Bernard Quaritch Ltd. (1847-)",
      "Abbey of St. Peter, Erfurt, Germany"
    ]
  },
  "Biblioteca Civica Anton Giulio Barrili": {
    "Matches": [],
    "Non-matches": []
  },
  "University of Michigan Library": {
    "Matches": [],
    "Non-matches": []
  },
  "Biblioteka Narodowa": {
    "Matches": [
      "Biblioteka Narodowa (Poland)"
    ],
    "Non-matches": [
      "Biblioteka Uniwersytecka w Warszawie"
    ]
  },
  " Staats- und Universit\u00e4tsbibliothek ": {
    "Matches": [],
    "Non-matches": [
      "K\u00f6nigliche \u00d6ffentliche Bibliothek zu Dresden"
    ]
  },
  "Biblioteca Marucelliana": {
    "Matches": [],
    "Non-matches": [
      "Biblioteca Medicea Laurenziana, Florence",
      "Biblioteca Nazionale Centrale, Firenze, Italy",
      "",
      "Firenze, Biblioteca Medicea Laurenziana",
      "Librairie Damasc\u00e8ne Morgand",
      "Pierpont Morgan Library",
      "Riccardi family",
      "Florence, Convento di San Marco"
    ]
  },
  "Bibliotheek der Rijksuniversiteit": {
    "Matches": [],
    "Non-matches": []
  },
  "Sconosciuta": {
    "Matches": [],
    "Non-matches": []
  },
  "Archivo y Biblioteca Capitulares": {
    "Matches": [],
    "Non-matches": []
  },
  " Section de M\u00e9decine": {
    "Matches": [],
    "Non-matches": []
  },
  "Biblioteca Malatestiana": {
    "Matches": [],
    "Non-matches": []
  },
  "St. Paul's Cathedral Library": {
    "Matches": [
      "London, cathedral church of St Paul"
    ],
    "Non-matches": [
      "Vente, London, Christie's, 2003, 26 mars, coll. Oswald Seilern",
      "Vente, London, Sotheby's, 1982, 21 juin",
      "British Museum",
      "Bury St Edmunds, Benedictine abbey",
      "LONDON, Lambeth Palace Library",
      "London Beth Din",
      "London, Bernard Quaritch Ltd. (1847-)",
      "Clare Priory",
      "Louvain, Park abbey",
      "Maggs (Librairie)",
      "Sotheby's (London, etc.)",
      "ABERDEEN, University Library",
      "Aberdeen, Marischal College",
      "S. Baker and G. Leigh",
      "Sam Fogg Rare Books & Manuscripts",
      "Bruxelles, Biblioth\u00e8que royale de Belgique",
      "Internationaal Antiquariaat (Menno Hertzberger & Co.)  (1920-1970)",
      "Clairvaux, Cistercian abbey",
      "Baltimore, The Walters Art Museum",
      "Walters Art Gallery",
      "Leo S. Olschki (Firm)",
      "Olschki",
      "De Bure",
      "Nosb\u00fcsch & Stucke (Firm)\u200f",
      "London, J. & J. Leighton",
      "Boston Medical Library",
      "Harvard Medical School",
      "Cambridge (Mass.), Harvard University",
      "Dawsons (libraire, Pall Mall, Londres)",
      "Robson & Co.",
      "Charles A. Stonehill, Inc.",
      "Payne and Foss",
      "MANCHESTER, John Rylands University Library",
      "Woodward family",
      "Les Enluminures Ltd.",
      "Idda Collection",
      "Reichskartause Buxheim (Carthusian monastery, Buxheim)",
      "Lambach, Notre-Dame & Saint-Chilian, abbaye, OSB",
      "Paul Graupe (Firm)",
      "University of Chicago (1890-)",
      "University of Chicago Library",
      "Cleveland Public Library",
      "London, Sion College",
      "London, Syon Abbey (Bridgettine)",
      "Syon Abbey (Devon, South Brent, England)",
      "Franciscans",
      "York Franciscan Friary",
      "York Minster Library",
      "University of Kansas",
      "E.P. Goldschmidt & Co.",
      "University of Liverpool. Library",
      "",
      "Phillipps manuscripts : Catalogus librorum manuscriptorum in bibliotheca D. Thomae Phillipps, Bt., impressum Typis Medio-Montanis, 1837-1871 (intro. by A.N.L. Munby)",
      "Principaux manusrits du cabinet M. Joseph-Louis-Dominique de Cambis",
      "Catalogue of the Manuscripts at Ashburnham Place: Appendix (C. Hodgson, Publisher)",
      "A Descriptive Catalogue of the Second Series of Fifty Manuscripts (Nos. 51 to 100) in the Collection of Henry Yates Thompson (Cambridge, 1902)",
      "The Last Flowering (French Paintings in Manuscripts)",
      "Sammlung und Verzeichniss handschriftlicher bucher...welche besitzt Leander van Ess",
      "Medieval Manuscripts in British Libraries, v.1, London (N.R.Ker)",
      "Catalogue of Manuscripts in the British Museum, N.S.1: Arundel (J. Forshall)",
      "Catalogue of the Library at Seaford House Belgrave Square S.W.",
      "Bibliotheca ms. Stowensis: a descriptive catalogue of the manuscripts in the Stowe library (Buckingham printed by J. Seeley, 1818-19)",
      "LONDON, British Library",
      "London, British Library, Sloane MS 1044",
      "Abbaye Saint-Martin (Tournai)  (652-1790)",
      "Bryn Mawr College",
      "Abbaye de Marmoutier (Tours)",
      "Pierpont Morgan Library",
      "Abbaye de Royaumont, Notre Dame, O. Cist (1228-1791)",
      "Ampleforth Abbey Trust",
      "Ampleforth Abbey",
      "Anderson Galleries, Inc.",
      "Antiquariaat Meijer Elte (Den Haag)",
      "Biblioteca Trivulziana",
      "Bloomsbury Book Auctions (Firm)",
      "Brown University",
      "CAMBRIDGE, Fitzwilliam Museum",
      "Christies",
      "Ellis & Elvey (librairie, Angleterre, fin 19e s.)",
      "Ellis",
      "Ely Cathedral",
      "Ghent, Sint-Pietersabdij, Benedictine abbey",
      "Long Island Historical Society",
      "George A. Leavitt & Co.",
      "H.M. Fletcher (Firm)",
      "Bergendal Collection",
      "Hartford Theological Seminary. Case Memorial Library",
      "Henry E. Huntington Library and Art Gallery.",
      "Hoepli (1870-)",
      "Monastery of S. Matteo de Caleis",
      "Potier",
      "Inner Temple",
      "Institution of Electrical Engineers",
      "J. I. Davis & G. M. Orioli (firm)",
      "Jacques Rosenthal (Firm)",
      "Law Society (Great Britain)",
      "Librairie et imprimerie Firmin Didot",
      "Boston, Public Library",
      "Gilhofer & Ranschburg, Vienna",
      "British Rail (Firm). Pension Fund",
      "H.P. Kraus (Firm)",
      "Canterbury Cathedral",
      "Cath\u00e9drale Notre-Dame de Tournai",
      "Biblioth\u00e8que de la Cath\u00e9drale Notre-Dame Tournai, Belgique",
      "Chartreuse dAubevoye",
      "Charles Sessler (Firm)",
      "Chester Beatty Library, Dublin",
      "Abbotsbury Abbey",
      "Wormsley Library",
      "Dawsons Book Shop",
      "Monteoliveto Maggiore, Benedictine Abbey",
      "Paris, Librairie Lardanchet (1912-)",
      "Charles W. Traylen (Firm)",
      "Princeton University",
      "Puttick & Simpson, maison de vente (London)",
      "Convent of St. Apolinaris",
      "Rebdorf Abbey",
      "Yale University",
      "Rosenthal",
      "William H. Robinson Limited",
      "Victoria and Albert Museum. National Art Library",
      "Victoria & Albert Museum",
      "Yale Law School",
      "London, British Library",
      "Abbey of St. Peter, Erfurt, Germany",
      "Canterbury, Benedictine abbey of St. Augustine",
      "Chester Cathedral",
      "Evesham, Benedictine abbey",
      "Llanthony Priory",
      "Ramsey, Benedictine Abbey",
      "Reading, Benedictine abbey",
      "Rievaulx Abbey (North Yorkshire, England)",
      "Rochester Cathedral",
      "St. Albans, Benedictine Abbey",
      "Tewkesbury, Benedictine Abbey",
      "Byrley, Thomas, active approximately 1500",
      "London, Sokol Books",
      "Monastery St. Ambrosius Major (Milan)",
      "Olympio\u0304tissa (Monastery : Elasson, Greece) ",
      "University of Pennsylvania, Library, Kislak Center for Special Collections, Rare Books and Manuscripts",
      "University of Pennsylvania",
      "Marcoussis, C\u00e9lestins",
      "Mus\u00e9e Napol\u00e9on",
      "National Archives (Great Britain)",
      "Librairie Salet (Salet-Soete)",
      "Plymouth Free Public Library",
      "ROMA, Biblioteca Nazionale Centrale 'Vittorio Emanuele II'",
      "Abbazia di Nonantola",
      "Biblioteca Sessoriana",
      "Roseberys",
      "Royal College of Physicians",
      "Sir John Soane's Museum",
      "Society of Antiquaries of London",
      "Soignies (Belgium), abbey and collegiate church of St. Vincent",
      "Stadtbibliothek K\u00f6nigsberg",
      "Solomons & Berkelouw",
      "Cleveland Museum of Art",
      "Sotheby Parke Bernet, Inc",
      "Silberstein-Boesky Charitable Foundation",
      "Sothebys New York",
      "Hellmut Schumann (Firm)",
      "Joseph Baer (Firm)",
      "Monasteriorum Allemanniae",
      "Origrafica Gallery",
      "Hartung & Karl",
      "Virtue and Cahill Library, St. John the Evangelist Roman Catholic Cathedral, Portsmouth",
      "Sotheby, Wilkinson & Hodge",
      "Southwark, Roman Catholic Metropolitan See",
      "Staatsbibliothek zu Berlin",
      "Beckford Collection, Hamilton Palace",
      "Carthusians of the Trinit\u00e9 (Dijon)",
      "K\u00f6nigliches Museum (Royal Museum), Berlin",
      "Stavelot, Saint-Pierre et Saint-Paul, puis Saint-R\u00e9macle, abbaye",
      "Techener",
      "University of London",
      "University College, London",
      "Weiss & Co. Antiquariat (Munich)",
      "Whalley Abbey (Whalley, England)",
      "Imperatorskai\ufe20a\ufe21 publichnai\ufe20a\ufe21 bibl\u012boteka (Saint Petersburg, Russia)",
      "LOS ANGELES, J. Paul Getty Museum",
      "Christie's",
      "St. Osyths Abbey, Essex",
      "Tollemache Library, Helmingham Hall",
      "New York, Public Library",
      "Schloss Jegenstorf (Jegenstorf, Switzerland)",
      "University of Notre Dame Library",
      "New York, The Brooklyn Museum",
      "Rome, church of Santa Cecilia in Trastevere",
      "Librairie Damasc\u00e8ne Morgand",
      "Rosenbach Museum & Library",
      "The Rosenbach Company",
      "Castle Howard (England)",
      "Martin Breslauer, Inc.",
      "Toledo Museum of Art",
      "Ch\u00e2teau de Rosny-sur-Seine. Biblioth\u00e8que",
      "Free Library of Philadelphia",
      "St Marys of the Barrens (Perryville, Missouri)",
      "University of Minnesota",
      "University of Illinois at Urbana-Champaign",
      "Lathrop C. Harper, Inc.",
      "Universit\u00e4tsbibliothek Basel ; Biblioth\u00e8que de B\u00e2le",
      "Hodegon Monastery",
      "Karl W. Hiersemann (Firm)"
    ]
  },
  "Biblioteca Ambrosiana": {
    "Matches": [
      "MILANO, Biblioteca Ambrosiana",
      "Milano, Biblioteca Ambrosiana",
      "Milano (I), Biblioteca Ambrosiana"
    ],
    "Non-matches": [
      "Biblioteca Trivulziana",
      "CAMBRIDGE, Fitzwilliam Museum",
      "Hoepli (1870-)",
      "University of Chicago (1890-)",
      "James & Mary Lee Tregaskis Booksellers",
      "Florence, Convento di San Marco",
      "University of Chicago Library",
      "Payne and Foss",
      "Chiesa di San Marco (Milan, Italy)",
      "",
      "Venezia, Biblioteca Nazionale Marciana",
      "Italy. Ministero della pubblica istruzione",
      "University of Notre Dame",
      "MILANO, Biblioteca Nazionale Braidense",
      "Biblioteca Estense (Modena, Italy)",
      "Morimondo, Cistercian abbey",
      "ROMA, Biblioteca Nazionale Centrale 'Vittorio Emanuele II'",
      "Archivio di Stato di Milano Fondo Galletti",
      "Libreria Antiquaria T. De Marinis",
      "J. Halle Antiquariat",
      "Kloster Lodi Vecchio",
      "Sola-Cabiati family",
      "William S. K\u00fcndig (Firm)",
      "Padua, Benedictine abbey of Santa Guistina",
      "Museo Cavaleri (Milan, Italy)\u200f",
      "Abbazia di San Sisto (Piacenza, Italy)",
      "Pierpont Morgan Library",
      "Abbaye de Morimond (Fresnoy-en-Bassigny, Haute-Marne)",
      "University of Pennsylvania, Library, Kislak Center for Special Collections, Rare Books and Manuscripts",
      "University of Pennsylvania"
    ]
  },
  "Biblioteca Vallicelliana": {
    "Matches": [
      "Biblioteca vallicelliana (Rome, Italy) "
    ],
    "Non-matches": [
      "Biblioteca angelica (Rome, Italy)",
      "Cambridge (Mass.), Harvard University",
      "Rome, Collegium Romanum Societatis Jesu",
      "Houghton Library",
      "",
      "Yale Law School",
      "Biblioteca comunale di Savigno di Romagna",
      "San Gregorio al Celio (Abbey : Rome, Italy)",
      "Southwark, Roman Catholic Metropolitan See",
      "'s-Gravenhage, Koninklijke Bibliotheek",
      "The Romantic Agony",
      "Tejada, Zerezo de"
    ]
  },
  "Archivio dell'Abbazia (Biblioteca Statale del Monumento Nazionale)": {
    "Matches": [],
    "Non-matches": [
      "Biblioth\u00e8que de la Facult\u00e9 de M\u00e9dicine (Montpellier)"
    ]
  },
  "Biblioteca Capitolare": {
    "Matches": [],
    "Non-matches": [
      "Basilica di SantAntonio (Padua, Italy) ",
      "Bibliothecae Patauinae manuscriptae publicae & priuatae ... (G.F. Tomasini)",
      "Padova, Bibliotheca Statale del Monumento Nazionale di Santa Giustina",
      "Padua, Bibliotheca R.R. P.P. Ordinis Eremitanorum S. Augustini"
    ]
  },
  "Bodleian Library": {
    "Matches": [
      "Oxford, The Bodleian Library",
      "OXFORD, Bodleian Library"
    ],
    "Non-matches": [
      "Oxford, Balliol College",
      "Catalogi librorum manuscriptorum angliae et hiberniae, v. 1 (E. Bernard)",
      "Catalogue of the printed books and manuscripts bequeathed by Francis Douce, esq.",
      "University of Oxford",
      "Canterbury, Christ Church Cathedral Priory (Benedictine)",
      "Oxford, Merton College",
      "Merton College MSS.",
      "Catalogi librorum manuscriptorum angliae et hiberniae, v. 2 (E. Bernard)",
      "Basel, Council of (1431-1449)"
    ]
  },
  "John Carter Brown Library": {
    "Matches": [],
    "Non-matches": []
  },
  "Universit\u00e4ts- und Landesbibliothek ": {
    "Matches": [],
    "Non-matches": []
  },
  "Biblioteca Universitaria ": {
    "Matches": [],
    "Non-matches": []
  },
  "Biblioth\u00e8que d'Agglom\u00e9ration du Pays de Saint-Omer": {
    "Matches": [],
    "Non-matches": []
  },
  "Biblioteca Universitaria y Biblioteca Historica de Santa Cruz": {
    "Matches": [],
    "Non-matches": []
  },
  "Benediktiner-Erzabtaei Sankt Peter Stiftsbibliothek": {
    "Matches": [],
    "Non-matches": []
  },
  "Biblioteca de la Universitat. Biblioteca Hist\u00f2rica": {
    "Matches": [],
    "Non-matches": [
      "Library San Miguel de Los Reyes",
      "Universidad de Valencia"
    ]
  },
  "Biblioteca Comunale": {
    "Matches": [],
    "Non-matches": []
  },
  "Biblioteca Venturi Ginori Lisci": {
    "Matches": [],
    "Non-matches": [
      "Biblioteca Nazionale Centrale, Firenze, Italy",
      "Riccardi family",
      "Florence, Convento di San Marco"
    ]
  },
  "Biblioth\u00e8que Mazarine": {
    "Matches": [
      "Paris (F), Biblioth\u00e8que Mazarine"
    ],
    "Non-matches": [
      "PARIS, Biblioth\u00e8que nationale de France, Manuscrits",
      "Coll\u00e8ge des Cholets (Paris)",
      "Paris, Jesuit college of Clermont",
      "Bergendal Collection",
      "De Bure",
      "Paris, Biblioth\u00e8que nationale de France, Manuscrits",
      "Sotheby, Wilkinson & Hodge"
    ]
  },
  "Biblioteca Statale del Monumento Nazionale di Montecassino": {
    "Matches": [],
    "Non-matches": []
  },
  " Kapituln\u00ed Knihovna": {
    "Matches": [],
    "Non-matches": []
  },
  "Minster Library": {
    "Matches": [
      "Reichskartause Buxheim (Carthusian monastery, Buxheim)",
      "York Minster Library"
    ],
    "Non-matches": [
      "Vente, New York, H.P. Kraus, 1978",
      "Biblioteca Trivulziana",
      "Omaha Public Library",
      "George A. Leavitt & Co.",
      "Bonhams (Firm)",
      "Christies New York",
      "Christie's",
      "Metropolitan Museum of Art (New York)",
      "Kirkham (Yorkshire), Augustinian priory",
      "",
      "Census of Medieval and Renaissance Manuscripts in the United States and Canada, vol. II (S. De Ricci)",
      "Cambridge (Mass.), Harvard University",
      "Rome, Collegium Romanum Societatis Jesu",
      "Houghton Library",
      "Columbia University",
      "Hispanic Society of America",
      "Jacques Rosenthal (Firm)",
      "Lathrop C. Harper, Inc.",
      "Charles Sessler (Firm)",
      "Henry E. Huntington Library and Art Gallery.",
      "Librairie et imprimerie Firmin Didot",
      "Olivetans",
      "San Gerolamo Abbey",
      "Pierpont Morgan Library",
      "Leo S. Olschki (Firm)",
      "London, Bernard Quaritch Ltd. (1847-)",
      "Boston, Public Library",
      "London, J. & J. Leighton",
      "Yale University",
      "Potier",
      "Montefiore Endowment",
      "Judith Montefiore College",
      "New York, Public Library",
      "Princeton University Art Museum",
      "Rosenthal",
      "United States. Alien Property Custodian",
      "Anderson Galleries, Inc.",
      "University of Kansas",
      "Yale Law School"
    ]
  },
  "Schloss Wolfegg": {
    "Matches": [],
    "Non-matches": []
  },
  "Biblioteca Nazionale Centrale Vittorio Emanuele II": {
    "Matches": [],
    "Non-matches": [
      "Catalogus selectissimae bibliothecae Nicholai Rossi, pt. 1",
      "Archivio di Stato di Roma"
    ]
  },
  "Biblioth\u00e8que de l'Universit\u00e9": {
    "Matches": [],
    "Non-matches": [
      "Abbey of Saint-Jacques, Liege",
      "National University of Ireland, Maynooth",
      "St. Patricks College (Maynooth, Ireland)"
    ]
  },
  "Biblioth\u00e8que Municipale\u00a0": {
    "Matches": [],
    "Non-matches": [
      "Catalogue general des manuscrits des bibliotheques publiques de France, v. 4, Bourges"
    ]
  },
  "Biblioteka Samostana Male Brace ": {
    "Matches": [],
    "Non-matches": []
  },
  "M\u00e9diath\u00e8que Voyelles ": {
    "Matches": [],
    "Non-matches": []
  },
  "Biblioteca del Monasterio de San Lorenzo El Real": {
    "Matches": [
      "El Escorial (E), Real Biblioteca del Monasterio de San Lorenzo"
    ],
    "Non-matches": []
  },
  "Biblioteca Nacional de Espa\u00f1a": {
    "Matches": [
      "Madrid, Biblioteca Nacional de Espa\u00f1a"
    ],
    "Non-matches": [
      "Real Academia de la Historia"
    ]
  },
  "Biblioteca Gennadios": {
    "Matches": [],
    "Non-matches": []
  },
  "Biblioteca Palatina": {
    "Matches": [],
    "Non-matches": []
  },
  "Museo Leone": {
    "Matches": [],
    "Non-matches": [
      "Archivio capitolare (Vercelli, Italy)"
    ]
  },
  "Biblioth\u00e8que Centrale Louis Aragon": {
    "Matches": [],
    "Non-matches": [
      "AMIENS, Biblioth\u00e8que municipale"
    ]
  },
  "Magdalen College Library": {
    "Matches": [
      "OXFORD, Magdalen College"
    ],
    "Non-matches": [
      "Cambridge (GB), Fitzwilliam Museum",
      "Catalogi librorum manuscriptorum angliae et hiberniae, v. 2 (E. Bernard)",
      "CAMBRIDGE, Parker Library (at Corpus Christi College)",
      "Canterbury, Benedictine abbey of St. Augustine",
      "Cambridge, University",
      "Les Enluminures Ltd.",
      "Chiaravalle della Colomba, Cistercian abbey (Alseno)",
      "Idda Collection",
      "Christies",
      "Episcopal Theological School (Cambridge, Mass.)",
      "CAMBRIDGE, Fitzwilliam Museum",
      "Sotheby's (London, etc.)",
      "LOS ANGELES, J. Paul Getty Museum",
      "Florence, Camaldolese convent of S. Maria degli Angeli",
      "Catalogi librorum manuscriptorum angliae et hiberniae, v. 1 (E. Bernard)",
      "Catalogue of the printed books and manuscripts bequeathed by Francis Douce, esq.",
      "Merton College MS. fragments"
    ]
  },
  "Biblioteca Regionale Universitaria": {
    "Matches": [],
    "Non-matches": []
  },
  "Cornell University Library": {
    "Matches": [],
    "Non-matches": []
  },
  "Merton College Library": {
    "Matches": [
      "Merton College MSS."
    ],
    "Non-matches": [
      "Catalogi librorum manuscriptorum angliae et hiberniae, v. 1 (E. Bernard)",
      "Catalogue of the printed books and manuscripts bequeathed by Francis Douce, esq."
    ]
  },
  "Jesus College Library": {
    "Matches": [
      "Jesus College MSS."
    ],
    "Non-matches": [
      "Chiaravalle de Bagnolo, Cistercian abbey (Milan)",
      "Campion Hall (University of Oxford)",
      "Catalogi librorum manuscriptorum angliae et hiberniae, v. 1 (E. Bernard)",
      "Catalogue of the printed books and manuscripts bequeathed by Francis Douce, esq.",
      "University of Oxford",
      "Winchcombe, Benedictine abbey"
    ]
  },
  "Biblioteca Civica Angelo Mai": {
    "Matches": [
      "Biblioteca Civica Angelo Mai di Bergamo"
    ],
    "Non-matches": [
      "BERN, Burgerbibliothek"
    ]
  },
  "Worcester College Library": {
    "Matches": [],
    "Non-matches": [
      "Catalogi librorum manuscriptorum angliae et hiberniae, v. 1 (E. Bernard)"
    ]
  },
  "Archivio Storico Diocesano": {
    "Matches": [],
    "Non-matches": []
  },
  "M\u00e9diath\u00e8que de la Communaut\u00e9 Urbaine": {
    "Matches": [],
    "Non-matches": []
  },
  "Biblioth\u00e8que de l'Arsenal": {
    "Matches": [
      "Paris (F), Biblioth\u00e8que de l'Arsenal",
      "Biblioth\u00e8que de lArsenal",
      "PARIS, Biblioth\u00e8que de l'Arsenal, 6259",
      "Paris, Biblioth\u00e8que de l'Arsenal"
    ],
    "Non-matches": [
      "PARIS, Biblioth\u00e8que nationale de France, Manuscrits",
      "France, Paris, Conservatoire national des arts et m\u00e9tiers. Biblioth\u00e8que Centrale",
      "Leiden, UB, Vossius lat. 4\u00b0 110 A + Vaticano, BAV, Reg. lat. 1709, ff. 34-35 + Paris, BnF, lat. 06400B",
      "Paris (F), Archives nationales",
      "Vente, Paris, Drouot, 2019, 18 novembre",
      "Abbaye Sainte-Genevi\u00e8ve (Paris)",
      "Bibliotheque Sainte-Genevieve (Paris, France) ",
      "Sankt-Peterburg (URSS), Rossijska\u00e2 Nacional'na\u00e2 Biblioteka",
      "Bruxelles, Biblioth\u00e8que royale de Belgique",
      "Abbey of Saint-Laurent, Liege",
      "Catalogue de la biblioth\u00e8que du coll\u00e8ge de Sorbonne (1338), I",
      "Catalogue de la biblioth\u00e8que du coll\u00e8ge de Sorbonne (1338), IX",
      "Catalogue de la biblioth\u00e8que du coll\u00e8ge de Sorbonne (1338), L",
      "Catalogue de la biblioth\u00e8que du coll\u00e8ge de Sorbonne (1338), XI",
      "Catalogue de la biblioth\u00e8que du coll\u00e8ge de Sorbonne (1338), XIII",
      "Catalogue de la biblioth\u00e8que du coll\u00e8ge de Sorbonne (1338), XLII",
      "Catalogue de la biblioth\u00e8que du coll\u00e8ge de Sorbonne (1338), XLVII",
      "Catalogue de la biblioth\u00e8que du coll\u00e8ge de Sorbonne (1338), XLVIII",
      "Catalogue de la biblioth\u00e8que du coll\u00e8ge de Sorbonne (1338), XV",
      "Catalogue de la biblioth\u00e8que du coll\u00e8ge de Sorbonne (1338), XVII",
      "Catalogue de la biblioth\u00e8que du coll\u00e8ge de Sorbonne (1338), XVIII",
      "Catalogue de la biblioth\u00e8que du coll\u00e8ge de Sorbonne (1338), XX",
      "Catalogue de la biblioth\u00e8que du coll\u00e8ge de Sorbonne (1338), XXI",
      "Catalogue de la biblioth\u00e8que du coll\u00e8ge de Sorbonne (1338), XXIV",
      "Catalogue de la biblioth\u00e8que du coll\u00e8ge de Sorbonne (1338), XXXIII",
      "Abbaye de Saint-Germain-des-Pr\u00e9s (Paris) (543-1794)",
      "Biblioth\u00e8que du roi (France)",
      "Coll\u00e8ge de Sorbonne (Paris)",
      "Paris, Jesuit college of Clermont",
      "Biblioth\u00e8que de la Sorbonne",
      "CAMBRIDGE, Fitzwilliam Museum",
      "London, Bernard Quaritch Ltd. (1847-)",
      "Notre-Dame de Paris (Cathedral)",
      "Bern, BB, Cod. 172 + Paris, BNF",
      "Bern, BB, Cod. 347, ff. 1\u201341 + Bern, BB, Cod. 357, ff. 33\u201343 + Leiden, UB, Voss. Lat. 4\u00b0 30, ff. 58, 57 + Paris, BnF, Lat. 7665, ff. 1\u201332 + Bern, BB, Cod. 357, ff. 1\u201332 + Bern, BB, Cod. 330",
      "Coll\u00e8ge des Cholets (Paris)",
      "Bergendal Collection",
      "Paris, Librairie Lardanchet (1912-)",
      "Librairie Sourget",
      "Les Enluminures Ltd.",
      "Librairie Damasc\u00e8ne Morgand",
      "Edinburgh, Royal Observatory",
      "Monastery of Great Lavra, Mount Athos (St. Athanasius)",
      "Mus\u00e9e du Louvre",
      "Puttick & Simpson, maison de vente (London)",
      "Weissenau Abbey",
      "Paris, Augustinian abbey of St.-Victor",
      "Philip C. Duschnes (Firm)",
      "Sam Fogg Rare Books & Manuscripts",
      "De Bure",
      "Yale University. Art Gallery",
      "Abbaye de Saint-Thierry-au-Mont-d'Or",
      "chartreuse de Paris",
      "Couvent Saint-Jacques (Paris ; 1217-1791)",
      "University of Oxford",
      "Gawsworth (Cheshire), parish church of St James",
      "",
      "A Catalogue of manuscripts forming a portion of the library of Robert Hoe (R. Hoe and C. Shipman)",
      "Paris, Biblioth\u00e8que de l'Institut de France",
      "Paris, Biblioth\u00e8que de la Sorbonne, RRA 3= 72",
      "Paris, Biblioth\u00e8que nationale de France, Manuscrits",
      "Paris, Biblioth\u00e8que nationale de France, Manuscrits, lat. 05062 + Vaticano (Citt\u00e0 del), Biblioteca apostolica Vaticana",
      "Paris, Conservatoire national des arts et m\u00e9tiers. Biblioth\u00e8que Centrale",
      "Paris, Biblioth\u00e8que nationale de France",
      "Artcurial : Briest, Poulain, Tajan",
      "Chateau de Bailleul",
      "Librairie Camille Sourget",
      "Baltimore, The Walters Art Museum",
      "Biblioth\u00e8que municipale de Tours",
      "Bonnefoi Livres Anciens",
      "Coll\u00e8ge de Foix (Toulouse)",
      "Paris, Conservatoire national des arts et m\u00e9tiers, Biblioth\u00e8que centrale",
      "Paris, Biblioth\u00e8que nationale de France, Manuscrits, lat. 07344A",
      "Librairie Salet (Salet-Soete)",
      "Du Quesnoy family",
      "Ellis and White",
      "Pierpont Morgan Library",
      "Gumuchian & cie",
      "Haverhill Public Library",
      "LOS ANGELES, J. Paul Getty Museum",
      "Leo S. Olschki (Firm)",
      "Olschki",
      "Librairie et imprimerie Firmin Didot",
      "Librairies Quentin & Forgeot",
      "Limoges, Saint-Sauveur, puis Saint-Martial, abbaye",
      "Lisbon, English College",
      "Boston, Public Library",
      "Payne and Foss",
      "Maggs (Librairie)",
      "Lewes Priory",
      "New York, Public Library",
      "Karl W. Hiersemann (Firm)",
      "Abbaye Saint-Pierre (Moissac, Tarn-et-Garonne ; 1052-1618)",
      "Abbaye de la No\u00eb (Evreux, France)",
      "Aragonese kings of Naples",
      "Biblioth\u00e8que royale de Blois",
      "Beaupre Abbey",
      "Cath\u00e9drale Notre-Dame (Le Puy, Haute-Loire, France)",
      "Chambre des Comptes de Blois",
      "Coll\u00e8ge des Carmes Paris",
      "Metz, Chapitre cath\u00e9dral",
      "Monast\u00e8re des C\u00e9lestins Paris",
      "Potier",
      "Sotheby's (London, etc.)",
      "College de Strasbourg",
      "Villeneuve-l\u00e8s-Avignon, Charterhouse of Val de B\u00e9n\u00e9diction",
      "Techener",
      "Salle Lebrun (Paris, France)",
      "Bibliotheque de Provins",
      "Abbaye Saint-Victor (Paris, 1113-1790)",
      "Edinburgh, National Library of Scotland",
      "Scottish Catholic Archives",
      "Scots College (Paris, France)",
      "Sotheby, Wilkinson & Hodge",
      "Alisi\u00e9 (Paris Bookseller)",
      "Free Library of Philadelphia",
      "Couvent Sainte-Croix-de-la-Bretonnerie (Paris)",
      "Sola Scriptura",
      "Holy Land Experience"
    ]
  },
  "Library of G\u00f6ttweig Abbey": {
    "Matches": [],
    "Non-matches": []
  },
  "Biblioteka Uniwersytecka": {
    "Matches": [
      "Biblioteka Uniwersytecka (Wroclaw)"
    ],
    "Non-matches": []
  },
  "\u00a0St. Patrick College of Kildare. Russell Library": {
    "Matches": [],
    "Non-matches": []
  },
  "Archiv Pra\u017esk\u00e9ho hradu": {
    "Matches": [],
    "Non-matches": []
  },
  "Herzog August Bibliothek": {
    "Matches": [
      "Herzog August Bibliothek"
    ],
    "Non-matches": []
  },
  "The Library of Trinity College": {
    "Matches": [],
    "Non-matches": [
      "Catalogi librorum manuscriptorum angliae et hiberniae, v. 2 (E. Bernard)"
    ]
  },
  "Biblioth\u00e8que d'Etude et du Patrimoine": {
    "Matches": [],
    "Non-matches": [
      "Biblioth\u00e8que municipale de Reims",
      "Reims (F), Biblioth\u00e8que municipale"
    ]
  },
  "\u00d6sterreichische Nationalbibliothek": {
    "Matches": [
      "\u00d6sterreichische Nationalbibliothek"
    ],
    "Non-matches": [
      "Dominikanerkloster (Vienna)",
      "Sotheby's (London, etc.)",
      "Collegium Ducale, University of Vienna",
      "Paul Graupe (Firm)",
      "Antiquariat Inlibris",
      "Gilhofer & Ranschburg, Vienna",
      ""
    ]
  },
  "Hoofdbibliotheek Biekorf": {
    "Matches": [],
    "Non-matches": [
      "Brugge, Archief Grootseminarie"
    ]
  },
  "Erzbisch\u00f6fliche Di\u00f6zesan- und Dombibliothek": {
    "Matches": [],
    "Non-matches": []
  },
  "St John's College Library": {
    "Matches": [],
    "Non-matches": [
      "CAMBRIDGE, Fitzwilliam Museum",
      "Catalogi librorum manuscriptorum angliae et hiberniae, v. 2 (E. Bernard)",
      "CAMBRIDGE, Parker Library (at Corpus Christi College)",
      "Canterbury, Benedictine abbey of St. Augustine",
      "St. Albans, Benedictine Abbey",
      "Newnham College",
      "London, Bernard Quaritch Ltd. (1847-)",
      "Abbey St Illidius (Clermont-Ferrand)",
      "Sotheby, Wilkinson & Hodge",
      "Burlington Fine Arts Club",
      "Census of Medieval and Renaissance Manuscripts in the United States and Canada, vol. I (S. De Ricci)",
      "Sherborne, abbey of S. Mary the Virgin (998-1539)",
      "Cambridge, University",
      "Paris, Librairie E. Caen, puis D. Morgand, puis Morgand et Fatout (1854-1924)",
      "Shrewsbury, Benedictine Abbey of St. Peter and St. Paul",
      "Malmesbury, Benedictine Abbey",
      "Rochester Cathedral",
      "Canterbury Cathedral"
    ]
  },
  "Fitzwilliam Museum": {
    "Matches": [],
    "Non-matches": []
  },
  "Biblioteca comunale Paolo Borsellino": {
    "Matches": [],
    "Non-matches": []
  },
  "Biblioteca Civica Guarneriana": {
    "Matches": [],
    "Non-matches": [
      "Biblioteca guarneriana di San Daniele del Friuli"
    ]
  },
  "Laurence Witten Rare Books": {
    "Matches": [],
    "Non-matches": []
  },
  "Bibliothek des Kapuzinerklosters": {
    "Matches": [],
    "Non-matches": []
  },
  "Biblioteca Nazionale Braidense": {
    "Matches": [
      "MILANO, Biblioteca Nazionale Braidense"
    ],
    "Non-matches": [
      "MILANO, Biblioteca Ambrosiana",
      "",
      "Hoepli (1870-)",
      "James & Mary Lee Tregaskis Booksellers",
      "Dukes of Urbino",
      "Archivio di Stato dellAquila",
      "Libreria Antiquaria T. De Marinis",
      "Ch\u00e2teau de Rosny-sur-Seine. Biblioth\u00e8que",
      "Archivio storico civico e Biblioteca trivulziana Milano"
    ]
  },
  "\u00a0Klosterbibliothek": {
    "Matches": [],
    "Non-matches": []
  },
  "National Library of Wales": {
    "Matches": [
      "Handlist of Manuscripts in the National Library of Wales, vol. II, pt. VII"
    ],
    "Non-matches": []
  },
  "Museum Plantin-Moretus - Bibliotheek": {
    "Matches": [],
    "Non-matches": []
  },
  "Biblioteca Citt\u00e0 di Arezzo": {
    "Matches": [],
    "Non-matches": []
  },
  "Universiteitsbibliotheek": {
    "Matches": [
      "Leiden, Universiteitsbibliotheek",
      "Leipzig, Universit\u00e4tsbibliothek"
    ],
    "Non-matches": [
      "Paris, Librairie Lardanchet (1912-)",
      "Les Enluminures Ltd.",
      "Librairie Damasc\u00e8ne Morgand",
      "",
      "Ellis and White",
      "Pierpont Morgan Library",
      "Leipziger Stadtbibliothek"
    ]
  },
  "Biblioteca Medicea Laurenziana": {
    "Matches": [
      "FIRENZE, Biblioteca Medicea Laurenziana",
      "Biblioteca Medicea Laurenziana, Florence"
    ],
    "Non-matches": [
      "Riccardi family",
      "Florence, Convento di San Marco",
      "Payne and Foss",
      "Yale University",
      "Leo S. Olschki (Firm)",
      "Ballarat Fine Art Gallery",
      "Biblioteca Nazionale Centrale, Firenze, Italy",
      "Firenze (I), Biblioteca Domenicana di Santa Maria Novella 'Jacopo Passavanti'",
      "",
      "Olschki",
      "Rosenthal",
      "Florence, Camaldolese convent of S. Maria degli Angeli",
      "Biblioteca Riccardiana",
      "Istituto italiano del libro (Florencja).",
      "Librairie et imprimerie Firmin Didot",
      "London, Bernard Quaritch Ltd. (1847-)",
      "London, J. & J. Leighton",
      "Libreria Antiquaria T. De Marinis",
      "A. Denham & Co.",
      "Oxford, The Bodleian Library",
      "University of Oxford",
      "CAMBRIDGE, Parker Library (at Corpus Christi College)",
      "LOS ANGELES, J. Paul Getty Museum",
      "Les Enluminures Ltd.",
      "Sotheby's (London, etc.)",
      "Florence, Badia Fiorentina, Benedictine abbey",
      "Librairie Damasc\u00e8ne Morgand",
      "Pierpont Morgan Library"
    ]
  },
  "Biblioteca comunale di Treviso": {
    "Matches": [],
    "Non-matches": []
  },
  "Gonville and Caius College Library": {
    "Matches": [],
    "Non-matches": []
  },
  "Univerzitetska biblioteka": {
    "Matches": [],
    "Non-matches": []
  },
  "Archivio Storico del Comune di Genova": {
    "Matches": [],
    "Non-matches": []
  },
  "Biblioteca Comunale degli Intronati": {
    "Matches": [
      "Siena, Biblioteca Comunale degli Intronati"
    ],
    "Non-matches": []
  },
  "Biblioteca P\u00fablica del Estado": {
    "Matches": [],
    "Non-matches": [
      "Monastery of Santa Maria de Santes Creus, Tarragona, Catalonia"
    ]
  },
  "Biblioth\u00e8que Marceline-Desbordes-Valmore": {
    "Matches": [],
    "Non-matches": []
  },
  "M\u00e9diath\u00e8que Jacques-Chirac": {
    "Matches": [],
    "Non-matches": []
  },
  "Zentralbibliothek": {
    "Matches": [
      "Z\u00fcrich, Zentralbibliothek"
    ],
    "Non-matches": []
  },
  " lettere ed arti": {
    "Matches": [],
    "Non-matches": [
      "Bibliothecae Patauinae manuscriptae publicae & priuatae ... (G.F. Tomasini)",
      "Basilica di SantAntonio (Padua, Italy) ",
      "Biblioteca capitolare di Padova",
      "Padua, Bibliotheca R.R. P.P. Ordinis Eremitanorum S. Augustini",
      "Padua, Bibliotheca S. Francisci",
      "Padua, Monastery of Saint John de Viridario",
      "Santa Maria in Vanzo"
    ]
  },
  "The Huntington Library": {
    "Matches": [],
    "Non-matches": []
  },
  "The Newberry Library": {
    "Matches": [
      "Chicago (USA), Newberry Library"
    ],
    "Non-matches": [
      "Les Enluminures Ltd.",
      "Puttick & Simpson, maison de vente (London)",
      "Sothebys New York",
      "Alde",
      "Librairie Sourget",
      "Bergendal Collection",
      "Koller Z\u00fcrich (Firm)",
      "Marc Antoine du Ry Medieval Art (Firm)",
      "Seminary library, S\u00e9es, Normandy",
      "Sotheby's (London, etc.)",
      "Rosenthal",
      "Tajan (Firm)",
      "Librairie Giraud-Badin",
      "Liesborn, Ss. Cosmas et Damian Abtei (815-1803)",
      "Bruce P. Ferrini (Firm)",
      "Idda Collection",
      "The Rosenbach Company",
      "Universit\u00e4t M\u00fcnster",
      "Christies New York",
      "Limoges, Saint-Sauveur, puis Saint-Martial, abbaye",
      "London, J. & J. Leighton",
      "San Gregorio al Celio (Abbey : Rome, Italy)",
      "H.P. Kraus (Firm)",
      "Maggs (Librairie)",
      "University of Chicago (1890-)",
      "University of Chicago Library",
      "Thomas Thorp (Firm)",
      "James & Mary Lee Tregaskis Booksellers",
      "Hoepli (1870-)",
      "Florence, Convento di San Marco",
      "Payne and Foss",
      "Chiesa di San Marco (Milan, Italy)",
      "S. Calvary & Co.",
      "",
      "Census of Medieval and Renaissance Manuscripts in the United States and Canada, vol. I (S. De Ricci)",
      "Bibliotheca Philosophica Hermetica",
      "Donald F. & Mildred Topp Othmer Library of Chemical History",
      "Hodgson's (1807-1967)",
      "Indiana University",
      "Emil Hirsch Antiquariat",
      "H\u00f4tel des ventes Drouot",
      "Ader, Picard, Tajan",
      "John Windle (Firm)",
      "Law Society (Great Britain)",
      "Abbazia di San Sisto (Piacenza, Italy)",
      "Antiquariaat Forum",
      "Cambridge, University",
      "Chiaravalle della Colomba, Cistercian abbey (Alseno)",
      "Christies",
      "Christie's",
      "Nonnberg Abbey",
      "Zisska & Kistner",
      "Haverhill Public Library",
      "Saint Blaise Abbey",
      "Sam Fogg Rare Books & Manuscripts",
      "Jews College",
      "London Beth Din",
      "Librairie et imprimerie Firmin Didot",
      "Paris, Librairie Lardanchet (1912-)",
      "London, Bernard Quaritch Ltd. (1847-)",
      "Charles W. Traylen (Firm)",
      "Librairie Damasc\u00e8ne Morgand",
      "Trinity College Dublin, Library",
      "J. I. Davis & G. M. Orioli (firm)",
      "Lutheran School of Theology at Chicago"
    ]
  },
  "Biblioteca Lodovico Jacobilli del Seminario Vescovile": {
    "Matches": [],
    "Non-matches": []
  },
  " Biblioth\u00e8que Inguimbertine": {
    "Matches": [
      "Biblioth\u00e8que inguimbertine de Carpentras"
    ],
    "Non-matches": []
  },
  "New College Library": {
    "Matches": [],
    "Non-matches": [
      "Catalogi librorum manuscriptorum angliae et hiberniae, v. 1 (E. Bernard)",
      "Catalogue of the printed books and manuscripts bequeathed by Francis Douce, esq."
    ]
  },
  "Biblioteca Civica": {
    "Matches": [],
    "Non-matches": [
      "London, Bernard Quaritch Ltd. (1847-)",
      "London, J. & J. Leighton",
      "Padua, Benedictine abbey of Santa Guistina",
      "Lathrop C. Harper, Inc.",
      "Dorling, F. (maison de vente, Hamburg)",
      "Hoepli (1870-)",
      "Dominican Convent of St. Augustine (Padua)",
      "Libreria Antiquaria T. De Marinis",
      "Santa Maria in Betlemme",
      "Santa Maria in Vanzo"
    ]
  },
  "Biblioth\u00e8que Inguimbertine": {
    "Matches": [],
    "Non-matches": []
  },
  " Knihovna Metropolitn\u00ed Kapituly": {
    "Matches": [],
    "Non-matches": [
      "N\u00e1rodn\u00ed knihovna \u010cesk\u00e9 republiky. Slovansk\u00e1 knihovna. (National Library of the Czech Republic)"
    ]
  },
  "Biblioteca Nazionale Vittorio Emanuele III": {
    "Matches": [],
    "Non-matches": [
      "PARIS, Biblioth\u00e8que nationale de France, Manuscrits",
      "Library of the Aragonese kings of Naples",
      "London, Bernard Quaritch Ltd. (1847-)",
      "Oxford, The Bodleian Library",
      "Collections Aristophil",
      "Arcana Collection",
      "Franciscan Holy Name College",
      "St. Bonaventure University",
      "Aragonese kings of Naples",
      "Biblioth\u00e8que royale de Blois"
    ]
  },
  "Biblioteca Estense Universitaria": {
    "Matches": [],
    "Non-matches": [
      "Biblioteca Estense (Modena, Italy)"
    ]
  },
  "Archivio Apostolico Vaticano": {
    "Matches": [],
    "Non-matches": []
  },
  "Knji\u017enica Hrvatske akademije znanosti i umjetnosti": {
    "Matches": [],
    "Non-matches": []
  },
  "Bibliothek des Domgymnasium": {
    "Matches": [],
    "Non-matches": []
  },
  " Archivio Provinciale dei Frati Minori": {
    "Matches": [],
    "Non-matches": [
      "Firenze (I), Biblioteca Domenicana di Santa Maria Novella 'Jacopo Passavanti'",
      "Biblioteca Nazionale Centrale, Firenze, Italy",
      "",
      "Leo S. Olschki (Firm)",
      "Olschki",
      "Riccardi family",
      "Yale University",
      "Rosenthal",
      "Florence, Convento di San Marco",
      "Florence, Camaldolese convent of S. Maria degli Angeli",
      "Payne and Foss"
    ]
  },
  "Zisterzienserstift Stiftsbibliothek": {
    "Matches": [],
    "Non-matches": []
  },
  "Koninklijke Bibliotheek": {
    "Matches": [],
    "Non-matches": [
      "Stads- of Athenaeumbibliotheek Deventer",
      "Antiquariaat Meijer Elte (Den Haag)"
    ]
  },
  "Biblioteca da Ajuda": {
    "Matches": [],
    "Non-matches": []
  },
  "Joseph Kusaila's Collection": {
    "Matches": [],
    "Non-matches": []
  },
  "Biblioteca Riccardiana": {
    "Matches": [
      "Biblioteca Riccardiana"
    ],
    "Non-matches": [
      "Biblioteca Medicea Laurenziana, Florence",
      "FIRENZE, Archivio di Stato",
      "Sotheby's (London, etc.)",
      "Florence, Convento di San Marco",
      "Payne and Foss"
    ]
  },
  "Biblioth\u00e8que du S\u00e9minaire Notre-Dame de Namur": {
    "Matches": [],
    "Non-matches": []
  },
  " James Ford Bell Collection": {
    "Matches": [],
    "Non-matches": []
  },
  "Dominikanski Samostan ": {
    "Matches": [],
    "Non-matches": []
  },
  "Biblioteca Angelica": {
    "Matches": [],
    "Non-matches": []
  },
  "Universit\u00e4ts- und Landesbibliothek": {
    "Matches": [],
    "Non-matches": [
      "",
      "MUENCHEN, Bayerische Staatsbibliothek"
    ]
  },
  "\u00a0Manuscript Division": {
    "Matches": [],
    "Non-matches": []
  },
  "Grand S\u00e9minaire": {
    "Matches": [],
    "Non-matches": []
  },
  "M\u00e9diath\u00e8que d'\u00c9pernay": {
    "Matches": [],
    "Non-matches": []
  },
  "Biblioteca Capitolare Feliniana": {
    "Matches": [],
    "Non-matches": []
  },
  "Biblioth\u00e8que Jacques Villon": {
    "Matches": [],
    "Non-matches": [
      "Biblioth\u00e8que municipale de Rouen"
    ]
  },
  "Public Library": {
    "Matches": [],
    "Non-matches": []
  },
  "Biblioteca Classense ": {
    "Matches": [
      "Biblioteca Comunale Classense (Ravenna, Italy)"
    ],
    "Non-matches": []
  },
  "Trinity College": {
    "Matches": [],
    "Non-matches": []
  },
  "KBR (Biblioth\u00e8que Royale de Belgique)": {
    "Matches": [
      "Bruxelles, Biblioth\u00e8que royale de Belgique"
    ],
    "Non-matches": []
  },
  "Nacionalna i sveu\u010dili\u0161na knji\u017enica u Zagrebu": {
    "Matches": [],
    "Non-matches": []
  },
  "Biblioteca dell'Accademia Nazionale dei Lincei e Corsiniana": {
    "Matches": [],
    "Non-matches": []
  },
  "Biblioteca Nazionale Universitaria": {
    "Matches": [],
    "Non-matches": [
      "Biblioteca de La Santa Iglesia Catedral (Tortosa)",
      "J. Pearson & Co."
    ]
  },
  "Biblioth\u00e8que Multim\u00e9dia Intercommunale Epinal-Goldbey ": {
    "Matches": [],
    "Non-matches": []
  },
  "Arxiu de la Corona d'Arag\u00f3": {
    "Matches": [
      "Archivo de la Corona di Aragon"
    ],
    "Non-matches": [
      "Universidad de Barcelona",
      "Convent San Jose (Barcelona)",
      "Barcelona, Biblioteca de Catalunya"
    ]
  },
  "University College Library": {
    "Matches": [],
    "Non-matches": [
      "Trinity College Dublin, Library",
      "Chester Beatty Library, Dublin",
      "Sotheby's (London, etc.)"
    ]
  }
}